{
  "id": "b34c2e27-707c-4d89-9a21-f1bcb7f9cdb1",
  "prevId": "00000000-0000-0000-0000-000000000000",
  "version": "6",
  "dialect": "postgresql",
  "tables": {
    "public.adjustments": {
      "name": "adjustments",
      "schema": "",
      "columns": {
        "id": {
          "name": "id",
          "type": "uuid",
          "primaryKey": true,
          "notNull": true,
          "default": "gen_random_uuid()"
        },
        "tenant_id": {
          "name": "tenant_id",
          "type": "uuid",
          "primaryKey": false,
          "notNull": true
        },
        "payout_id": {
          "name": "payout_id",
          "type": "uuid",
          "primaryKey": false,
          "notNull": true
        },
        "dispute_id": {
          "name": "dispute_id",
          "type": "uuid",
          "primaryKey": false,
          "notNull": false
        },
        "approval_request_id": {
          "name": "approval_request_id",
          "type": "uuid",
          "primaryKey": false,
          "notNull": false
        },
        "type": {
          "name": "type",
          "type": "text",
          "primaryKey": false,
          "notNull": true
        },
        "amount_cents": {
          "name": "amount_cents",
          "type": "integer",
          "primaryKey": false,
          "notNull": true
        },
        "currency": {
          "name": "currency",
          "type": "text",
          "primaryKey": false,
          "notNull": true,
          "default": "'USD'"
        },
        "reason": {
          "name": "reason",
          "type": "text",
          "primaryKey": false,
          "notNull": true
        },
        "applied_by_id": {
          "name": "applied_by_id",
          "type": "uuid",
          "primaryKey": false,
          "notNull": true
        },
        "applied_at": {
          "name": "applied_at",
          "type": "timestamp with time zone",
          "primaryKey": false,
          "notNull": true
        },
        "created_at": {
          "name": "created_at",
          "type": "timestamp with time zone",
          "primaryKey": false,
          "notNull": true,
          "default": "now()"
        },
        "updated_at": {
          "name": "updated_at",
          "type": "timestamp with time zone",
          "primaryKey": false,
          "notNull": true,
          "default": "now()"
        }
      },
      "indexes": {},
      "foreignKeys": {
        "adjustments_payout_id_payouts_id_fk": {
          "name": "adjustments_payout_id_payouts_id_fk",
          "tableFrom": "adjustments",
          "tableTo": "payouts",
          "columnsFrom": [
            "payout_id"
          ],
          "columnsTo": [
            "id"
          ],
          "onDelete": "no action",
          "onUpdate": "no action"
        },
        "adjustments_dispute_id_disputes_id_fk": {
          "name": "adjustments_dispute_id_disputes_id_fk",
          "tableFrom": "adjustments",
          "tableTo": "disputes",
          "columnsFrom": [
            "dispute_id"
          ],
          "columnsTo": [
            "id"
          ],
          "onDelete": "no action",
          "onUpdate": "no action"
        },
        "adjustments_approval_request_id_approval_requests_id_fk": {
          "name": "adjustments_approval_request_id_approval_requests_id_fk",
          "tableFrom": "adjustments",
          "tableTo": "approval_requests",
          "columnsFrom": [
            "approval_request_id"
          ],
          "columnsTo": [
            "id"
          ],
          "onDelete": "no action",
          "onUpdate": "no action"
        },
        "adjustments_applied_by_id_users_id_fk": {
          "name": "adjustments_applied_by_id_users_id_fk",
          "tableFrom": "adjustments",
          "tableTo": "users",
          "columnsFrom": [
            "applied_by_id"
          ],
          "columnsTo": [
            "id"
          ],
          "onDelete": "no action",
          "onUpdate": "no action"
        }
      },
      "compositePrimaryKeys": {},
      "uniqueConstraints": {}
    },
    "public.approval_requests": {
      "name": "approval_requests",
      "schema": "",
      "columns": {
        "id": {
          "name": "id",
          "type": "uuid",
          "primaryKey": true,
          "notNull": true,
          "default": "gen_random_uuid()"
        },
        "tenant_id": {
          "name": "tenant_id",
          "type": "uuid",
          "primaryKey": false,
          "notNull": true
        },
        "workflow_type": {
          "name": "workflow_type",
          "type": "text",
          "primaryKey": false,
          "notNull": true
        },
        "entity_type": {
          "name": "entity_type",
          "type": "text",
          "primaryKey": false,
          "notNull": true
        },
        "entity_id": {
          "name": "entity_id",
          "type": "uuid",
          "primaryKey": false,
          "notNull": true
        },
        "requested_by_id": {
          "name": "requested_by_id",
          "type": "uuid",
          "primaryKey": false,
          "notNull": true
        },
        "assigned_to_id": {
          "name": "assigned_to_id",
          "type": "uuid",
          "primaryKey": false,
          "notNull": false
        },
        "status": {
          "name": "status",
          "type": "text",
          "primaryKey": false,
          "notNull": true,
          "default": "'pending'"
        },
        "due_at": {
          "name": "due_at",
          "type": "timestamp with time zone",
          "primaryKey": false,
          "notNull": false
        },
        "decided_at": {
          "name": "decided_at",
          "type": "timestamp with time zone",
          "primaryKey": false,
          "notNull": false
        },
        "decided_by_id": {
          "name": "decided_by_id",
          "type": "uuid",
          "primaryKey": false,
          "notNull": false
        },
        "notes": {
          "name": "notes",
          "type": "text",
          "primaryKey": false,
          "notNull": false
        },
        "created_at": {
          "name": "created_at",
          "type": "timestamp with time zone",
          "primaryKey": false,
          "notNull": true,
          "default": "now()"
        },
        "updated_at": {
          "name": "updated_at",
          "type": "timestamp with time zone",
          "primaryKey": false,
          "notNull": true,
          "default": "now()"
        }
      },
      "indexes": {},
      "foreignKeys": {
        "approval_requests_requested_by_id_users_id_fk": {
          "name": "approval_requests_requested_by_id_users_id_fk",
          "tableFrom": "approval_requests",
          "tableTo": "users",
          "columnsFrom": [
            "requested_by_id"
          ],
          "columnsTo": [
            "id"
          ],
          "onDelete": "no action",
          "onUpdate": "no action"
        },
        "approval_requests_assigned_to_id_users_id_fk": {
          "name": "approval_requests_assigned_to_id_users_id_fk",
          "tableFrom": "approval_requests",
          "tableTo": "users",
          "columnsFrom": [
            "assigned_to_id"
          ],
          "columnsTo": [
            "id"
          ],
          "onDelete": "no action",
          "onUpdate": "no action"
        },
        "approval_requests_decided_by_id_users_id_fk": {
          "name": "approval_requests_decided_by_id_users_id_fk",
          "tableFrom": "approval_requests",
          "tableTo": "users",
          "columnsFrom": [
            "decided_by_id"
          ],
          "columnsTo": [
            "id"
          ],
          "onDelete": "no action",
          "onUpdate": "no action"
        }
      },
      "compositePrimaryKeys": {},
      "uniqueConstraints": {}
    },
    "public.audit_events": {
      "name": "audit_events",
      "schema": "",
      "columns": {
        "id": {
          "name": "id",
          "type": "uuid",
          "primaryKey": true,
          "notNull": true,
          "default": "gen_random_uuid()"
        },
        "tenant_id": {
          "name": "tenant_id",
          "type": "uuid",
          "primaryKey": false,
          "notNull": true
        },
        "entity_type": {
          "name": "entity_type",
          "type": "text",
          "primaryKey": false,
          "notNull": true
        },
        "entity_id": {
          "name": "entity_id",
          "type": "uuid",
          "primaryKey": false,
          "notNull": true
        },
        "action": {
          "name": "action",
          "type": "text",
          "primaryKey": false,
          "notNull": true
        },
        "actor_id": {
          "name": "actor_id",
          "type": "uuid",
          "primaryKey": false,
          "notNull": false
        },
        "actor_type": {
          "name": "actor_type",
          "type": "text",
          "primaryKey": false,
          "notNull": true,
          "default": "'user'"
        },
        "before": {
          "name": "before",
          "type": "jsonb",
          "primaryKey": false,
          "notNull": false
        },
        "after": {
          "name": "after",
          "type": "jsonb",
          "primaryKey": false,
          "notNull": false
        },
        "metadata": {
          "name": "metadata",
          "type": "jsonb",
          "primaryKey": false,
          "notNull": true,
          "default": "'{}'::jsonb"
        },
        "occurred_at": {
          "name": "occurred_at",
          "type": "timestamp with time zone",
          "primaryKey": false,
          "notNull": true,
          "default": "now()"
        }
      },
      "indexes": {},
      "foreignKeys": {},
      "compositePrimaryKeys": {},
      "uniqueConstraints": {}
    },
    "public.calculation_runs": {
      "name": "calculation_runs",
      "schema": "",
      "columns": {
        "id": {
          "name": "id",
          "type": "uuid",
          "primaryKey": true,
          "notNull": true,
          "default": "gen_random_uuid()"
        },
        "tenant_id": {
          "name": "tenant_id",
          "type": "uuid",
          "primaryKey": false,
          "notNull": true
        },
        "period_id": {
          "name": "period_id",
          "type": "uuid",
          "primaryKey": false,
          "notNull": true
        },
        "plan_version_id": {
          "name": "plan_version_id",
          "type": "uuid",
          "primaryKey": false,
          "notNull": false
        },
        "status": {
          "name": "status",
          "type": "text",
          "primaryKey": false,
          "notNull": true,
          "default": "'queued'"
        },
        "triggered_by_id": {
          "name": "triggered_by_id",
          "type": "uuid",
          "primaryKey": false,
          "notNull": false
        },
        "started_at": {
          "name": "started_at",
          "type": "timestamp with time zone",
          "primaryKey": false,
          "notNull": false
        },
        "completed_at": {
          "name": "completed_at",
          "type": "timestamp with time zone",
          "primaryKey": false,
          "notNull": false
        },
        "participant_count": {
          "name": "participant_count",
          "type": "integer",
          "primaryKey": false,
          "notNull": true,
          "default": 0
        },
        "error_count": {
          "name": "error_count",
          "type": "integer",
          "primaryKey": false,
          "notNull": true,
          "default": 0
        },
        "config": {
          "name": "config",
          "type": "jsonb",
          "primaryKey": false,
          "notNull": true,
          "default": "'{}'::jsonb"
        },
        "created_at": {
          "name": "created_at",
          "type": "timestamp with time zone",
          "primaryKey": false,
          "notNull": true,
          "default": "now()"
        },
        "updated_at": {
          "name": "updated_at",
          "type": "timestamp with time zone",
          "primaryKey": false,
          "notNull": true,
          "default": "now()"
        }
      },
      "indexes": {},
      "foreignKeys": {
        "calculation_runs_period_id_periods_id_fk": {
          "name": "calculation_runs_period_id_periods_id_fk",
          "tableFrom": "calculation_runs",
          "tableTo": "periods",
          "columnsFrom": [
            "period_id"
          ],
          "columnsTo": [
            "id"
          ],
          "onDelete": "no action",
          "onUpdate": "no action"
        },
        "calculation_runs_plan_version_id_plan_versions_id_fk": {
          "name": "calculation_runs_plan_version_id_plan_versions_id_fk",
          "tableFrom": "calculation_runs",
          "tableTo": "plan_versions",
          "columnsFrom": [
            "plan_version_id"
          ],
          "columnsTo": [
            "id"
          ],
          "onDelete": "no action",
          "onUpdate": "no action"
        },
        "calculation_runs_triggered_by_id_users_id_fk": {
          "name": "calculation_runs_triggered_by_id_users_id_fk",
          "tableFrom": "calculation_runs",
          "tableTo": "users",
          "columnsFrom": [
            "triggered_by_id"
          ],
          "columnsTo": [
            "id"
          ],
          "onDelete": "no action",
          "onUpdate": "no action"
        }
      },
      "compositePrimaryKeys": {},
      "uniqueConstraints": {}
    },
    "public.components": {
      "name": "components",
      "schema": "",
      "columns": {
        "id": {
          "name": "id",
          "type": "uuid",
          "primaryKey": true,
          "notNull": true,
          "default": "gen_random_uuid()"
        },
        "tenant_id": {
          "name": "tenant_id",
          "type": "uuid",
          "primaryKey": false,
          "notNull": true
        },
        "plan_version_id": {
          "name": "plan_version_id",
          "type": "uuid",
          "primaryKey": false,
          "notNull": true
        },
        "name": {
          "name": "name",
          "type": "text",
          "primaryKey": false,
          "notNull": true
        },
        "type": {
          "name": "type",
          "type": "text",
          "primaryKey": false,
          "notNull": true
        },
        "measure_type": {
          "name": "measure_type",
          "type": "text",
          "primaryKey": false,
          "notNull": false
        },
        "formula_id": {
          "name": "formula_id",
          "type": "text",
          "primaryKey": false,
          "notNull": false
        },
        "config": {
          "name": "config",
          "type": "jsonb",
          "primaryKey": false,
          "notNull": true,
          "default": "'{}'::jsonb"
        },
        "sort_order": {
          "name": "sort_order",
          "type": "integer",
          "primaryKey": false,
          "notNull": true,
          "default": 0
        },
        "created_at": {
          "name": "created_at",
          "type": "timestamp with time zone",
          "primaryKey": false,
          "notNull": true,
          "default": "now()"
        },
        "updated_at": {
          "name": "updated_at",
          "type": "timestamp with time zone",
          "primaryKey": false,
          "notNull": true,
          "default": "now()"
        }
      },
      "indexes": {},
      "foreignKeys": {
        "components_plan_version_id_plan_versions_id_fk": {
          "name": "components_plan_version_id_plan_versions_id_fk",
          "tableFrom": "components",
          "tableTo": "plan_versions",
          "columnsFrom": [
            "plan_version_id"
          ],
          "columnsTo": [
            "id"
          ],
          "onDelete": "no action",
          "onUpdate": "no action"
        }
      },
      "compositePrimaryKeys": {},
      "uniqueConstraints": {}
    },
    "public.credits": {
      "name": "credits",
      "schema": "",
      "columns": {
        "id": {
          "name": "id",
          "type": "uuid",
          "primaryKey": true,
          "notNull": true,
          "default": "gen_random_uuid()"
        },
        "tenant_id": {
          "name": "tenant_id",
          "type": "uuid",
          "primaryKey": false,
          "notNull": true
        },
        "transaction_id": {
          "name": "transaction_id",
          "type": "uuid",
          "primaryKey": false,
          "notNull": true
        },
        "participant_id": {
          "name": "participant_id",
          "type": "uuid",
          "primaryKey": false,
          "notNull": true
        },
        "component_id": {
          "name": "component_id",
          "type": "uuid",
          "primaryKey": false,
          "notNull": true
        },
        "period_id": {
          "name": "period_id",
          "type": "uuid",
          "primaryKey": false,
          "notNull": true
        },
        "amount_cents": {
          "name": "amount_cents",
          "type": "integer",
          "primaryKey": false,
          "notNull": true
        },
        "currency": {
          "name": "currency",
          "type": "text",
          "primaryKey": false,
          "notNull": true,
          "default": "'USD'"
        },
        "credit_rule_id": {
          "name": "credit_rule_id",
          "type": "text",
          "primaryKey": false,
          "notNull": false
        },
        "split_pct": {
          "name": "split_pct",
          "type": "integer",
          "primaryKey": false,
          "notNull": true,
          "default": 100
        },
        "metadata": {
          "name": "metadata",
          "type": "jsonb",
          "primaryKey": false,
          "notNull": true,
          "default": "'{}'::jsonb"
        },
        "created_at": {
          "name": "created_at",
          "type": "timestamp with time zone",
          "primaryKey": false,
          "notNull": true,
          "default": "now()"
        },
        "updated_at": {
          "name": "updated_at",
          "type": "timestamp with time zone",
          "primaryKey": false,
          "notNull": true,
          "default": "now()"
        }
      },
      "indexes": {},
      "foreignKeys": {
        "credits_transaction_id_source_transactions_id_fk": {
          "name": "credits_transaction_id_source_transactions_id_fk",
          "tableFrom": "credits",
          "tableTo": "source_transactions",
          "columnsFrom": [
            "transaction_id"
          ],
          "columnsTo": [
            "id"
          ],
          "onDelete": "no action",
          "onUpdate": "no action"
        },
        "credits_participant_id_participants_id_fk": {
          "name": "credits_participant_id_participants_id_fk",
          "tableFrom": "credits",
          "tableTo": "participants",
          "columnsFrom": [
            "participant_id"
          ],
          "columnsTo": [
            "id"
          ],
          "onDelete": "no action",
          "onUpdate": "no action"
        },
        "credits_component_id_components_id_fk": {
          "name": "credits_component_id_components_id_fk",
          "tableFrom": "credits",
          "tableTo": "components",
          "columnsFrom": [
            "component_id"
          ],
          "columnsTo": [
            "id"
          ],
          "onDelete": "no action",
          "onUpdate": "no action"
        },
        "credits_period_id_periods_id_fk": {
          "name": "credits_period_id_periods_id_fk",
          "tableFrom": "credits",
          "tableTo": "periods",
          "columnsFrom": [
            "period_id"
          ],
          "columnsTo": [
            "id"
          ],
          "onDelete": "no action",
          "onUpdate": "no action"
        }
      },
      "compositePrimaryKeys": {},
      "uniqueConstraints": {}
    },
    "public.disputes": {
      "name": "disputes",
      "schema": "",
      "columns": {
        "id": {
          "name": "id",
          "type": "uuid",
          "primaryKey": true,
          "notNull": true,
          "default": "gen_random_uuid()"
        },
        "tenant_id": {
          "name": "tenant_id",
          "type": "uuid",
          "primaryKey": false,
          "notNull": true
        },
        "payout_id": {
          "name": "payout_id",
          "type": "uuid",
          "primaryKey": false,
          "notNull": false
        },
        "transaction_id": {
          "name": "transaction_id",
          "type": "uuid",
          "primaryKey": false,
          "notNull": false
        },
        "participant_id": {
          "name": "participant_id",
          "type": "uuid",
          "primaryKey": false,
          "notNull": true
        },
        "opened_by_id": {
          "name": "opened_by_id",
          "type": "uuid",
          "primaryKey": false,
          "notNull": true
        },
        "assigned_to_id": {
          "name": "assigned_to_id",
          "type": "uuid",
          "primaryKey": false,
          "notNull": false
        },
        "status": {
          "name": "status",
          "type": "text",
          "primaryKey": false,
          "notNull": true,
          "default": "'open'"
        },
        "subject": {
          "name": "subject",
          "type": "text",
          "primaryKey": false,
          "notNull": true
        },
        "description": {
          "name": "description",
          "type": "text",
          "primaryKey": false,
          "notNull": true
        },
        "requested_amount_cents": {
          "name": "requested_amount_cents",
          "type": "integer",
          "primaryKey": false,
          "notNull": false
        },
        "requested_currency": {
          "name": "requested_currency",
          "type": "text",
          "primaryKey": false,
          "notNull": false
        },
        "resolved_amount_cents": {
          "name": "resolved_amount_cents",
          "type": "integer",
          "primaryKey": false,
          "notNull": false
        },
        "resolved_currency": {
          "name": "resolved_currency",
          "type": "text",
          "primaryKey": false,
          "notNull": false
        },
        "resolved_at": {
          "name": "resolved_at",
          "type": "timestamp with time zone",
          "primaryKey": false,
          "notNull": false
        },
        "resolved_by_id": {
          "name": "resolved_by_id",
          "type": "uuid",
          "primaryKey": false,
          "notNull": false
        },
        "resolution_notes": {
          "name": "resolution_notes",
          "type": "text",
          "primaryKey": false,
          "notNull": false
        },
        "created_at": {
          "name": "created_at",
          "type": "timestamp with time zone",
          "primaryKey": false,
          "notNull": true,
          "default": "now()"
        },
        "updated_at": {
          "name": "updated_at",
          "type": "timestamp with time zone",
          "primaryKey": false,
          "notNull": true,
          "default": "now()"
        }
      },
      "indexes": {},
      "foreignKeys": {
        "disputes_payout_id_payouts_id_fk": {
          "name": "disputes_payout_id_payouts_id_fk",
          "tableFrom": "disputes",
          "tableTo": "payouts",
          "columnsFrom": [
            "payout_id"
          ],
          "columnsTo": [
            "id"
          ],
          "onDelete": "no action",
          "onUpdate": "no action"
        },
        "disputes_transaction_id_source_transactions_id_fk": {
          "name": "disputes_transaction_id_source_transactions_id_fk",
          "tableFrom": "disputes",
          "tableTo": "source_transactions",
          "columnsFrom": [
            "transaction_id"
          ],
          "columnsTo": [
            "id"
          ],
          "onDelete": "no action",
          "onUpdate": "no action"
        },
        "disputes_participant_id_participants_id_fk": {
          "name": "disputes_participant_id_participants_id_fk",
          "tableFrom": "disputes",
          "tableTo": "participants",
          "columnsFrom": [
            "participant_id"
          ],
          "columnsTo": [
            "id"
          ],
          "onDelete": "no action",
          "onUpdate": "no action"
        },
        "disputes_opened_by_id_users_id_fk": {
          "name": "disputes_opened_by_id_users_id_fk",
          "tableFrom": "disputes",
          "tableTo": "users",
          "columnsFrom": [
            "opened_by_id"
          ],
          "columnsTo": [
            "id"
          ],
          "onDelete": "no action",
          "onUpdate": "no action"
        },
        "disputes_assigned_to_id_users_id_fk": {
          "name": "disputes_assigned_to_id_users_id_fk",
          "tableFrom": "disputes",
          "tableTo": "users",
          "columnsFrom": [
            "assigned_to_id"
          ],
          "columnsTo": [
            "id"
          ],
          "onDelete": "no action",
          "onUpdate": "no action"
        },
        "disputes_resolved_by_id_users_id_fk": {
          "name": "disputes_resolved_by_id_users_id_fk",
          "tableFrom": "disputes",
          "tableTo": "users",
          "columnsFrom": [
            "resolved_by_id"
          ],
          "columnsTo": [
            "id"
          ],
          "onDelete": "no action",
          "onUpdate": "no action"
        }
      },
      "compositePrimaryKeys": {},
      "uniqueConstraints": {}
    },
    "public.goal_sheets": {
      "name": "goal_sheets",
      "schema": "",
      "columns": {
        "id": {
          "name": "id",
          "type": "uuid",
          "primaryKey": true,
          "notNull": true,
          "default": "gen_random_uuid()"
        },
        "tenant_id": {
          "name": "tenant_id",
          "type": "uuid",
          "primaryKey": false,
          "notNull": true
        },
        "participant_id": {
          "name": "participant_id",
          "type": "uuid",
          "primaryKey": false,
          "notNull": true
        },
        "plan_version_id": {
          "name": "plan_version_id",
          "type": "uuid",
          "primaryKey": false,
          "notNull": true
        },
        "period_id": {
          "name": "period_id",
          "type": "uuid",
          "primaryKey": false,
          "notNull": true
        },
        "status": {
          "name": "status",
          "type": "text",
          "primaryKey": false,
          "notNull": true,
          "default": "'draft'"
        },
        "distributed_at": {
          "name": "distributed_at",
          "type": "timestamp with time zone",
          "primaryKey": false,
          "notNull": false
        },
        "acknowledged_at": {
          "name": "acknowledged_at",
          "type": "timestamp with time zone",
          "primaryKey": false,
          "notNull": false
        },
        "acknowledged_by_id": {
          "name": "acknowledged_by_id",
          "type": "uuid",
          "primaryKey": false,
          "notNull": false
        },
        "file_id": {
          "name": "file_id",
          "type": "uuid",
          "primaryKey": false,
          "notNull": false
        },
        "data": {
          "name": "data",
          "type": "jsonb",
          "primaryKey": false,
          "notNull": true,
          "default": "'{}'::jsonb"
        },
        "created_at": {
          "name": "created_at",
          "type": "timestamp with time zone",
          "primaryKey": false,
          "notNull": true,
          "default": "now()"
        },
        "updated_at": {
          "name": "updated_at",
          "type": "timestamp with time zone",
          "primaryKey": false,
          "notNull": true,
          "default": "now()"
        }
      },
      "indexes": {},
      "foreignKeys": {
        "goal_sheets_participant_id_participants_id_fk": {
          "name": "goal_sheets_participant_id_participants_id_fk",
          "tableFrom": "goal_sheets",
          "tableTo": "participants",
          "columnsFrom": [
            "participant_id"
          ],
          "columnsTo": [
            "id"
          ],
          "onDelete": "no action",
          "onUpdate": "no action"
        },
        "goal_sheets_plan_version_id_plan_versions_id_fk": {
          "name": "goal_sheets_plan_version_id_plan_versions_id_fk",
          "tableFrom": "goal_sheets",
          "tableTo": "plan_versions",
          "columnsFrom": [
            "plan_version_id"
          ],
          "columnsTo": [
            "id"
          ],
          "onDelete": "no action",
          "onUpdate": "no action"
        },
        "goal_sheets_period_id_periods_id_fk": {
          "name": "goal_sheets_period_id_periods_id_fk",
          "tableFrom": "goal_sheets",
          "tableTo": "periods",
          "columnsFrom": [
            "period_id"
          ],
          "columnsTo": [
            "id"
          ],
          "onDelete": "no action",
          "onUpdate": "no action"
        },
        "goal_sheets_acknowledged_by_id_users_id_fk": {
          "name": "goal_sheets_acknowledged_by_id_users_id_fk",
          "tableFrom": "goal_sheets",
          "tableTo": "users",
          "columnsFrom": [
            "acknowledged_by_id"
          ],
          "columnsTo": [
            "id"
          ],
          "onDelete": "no action",
          "onUpdate": "no action"
        }
      },
      "compositePrimaryKeys": {},
      "uniqueConstraints": {}
    },
    "public.notifications": {
      "name": "notifications",
      "schema": "",
      "columns": {
        "id": {
          "name": "id",
          "type": "uuid",
          "primaryKey": true,
          "notNull": true,
          "default": "gen_random_uuid()"
        },
        "tenant_id": {
          "name": "tenant_id",
          "type": "uuid",
          "primaryKey": false,
          "notNull": true
        },
        "recipient_id": {
          "name": "recipient_id",
          "type": "uuid",
          "primaryKey": false,
          "notNull": true
        },
        "type": {
          "name": "type",
          "type": "text",
          "primaryKey": false,
          "notNull": true
        },
        "title": {
          "name": "title",
          "type": "text",
          "primaryKey": false,
          "notNull": true
        },
        "body": {
          "name": "body",
          "type": "text",
          "primaryKey": false,
          "notNull": true
        },
        "is_read": {
          "name": "is_read",
          "type": "boolean",
          "primaryKey": false,
          "notNull": true,
          "default": false
        },
        "read_at": {
          "name": "read_at",
          "type": "timestamp with time zone",
          "primaryKey": false,
          "notNull": false
        },
        "metadata": {
          "name": "metadata",
          "type": "jsonb",
          "primaryKey": false,
          "notNull": true,
          "default": "'{}'::jsonb"
        },
        "created_at": {
          "name": "created_at",
          "type": "timestamp with time zone",
          "primaryKey": false,
          "notNull": true,
          "default": "now()"
        }
      },
      "indexes": {},
      "foreignKeys": {
        "notifications_recipient_id_users_id_fk": {
          "name": "notifications_recipient_id_users_id_fk",
          "tableFrom": "notifications",
          "tableTo": "users",
          "columnsFrom": [
            "recipient_id"
          ],
          "columnsTo": [
            "id"
          ],
          "onDelete": "no action",
          "onUpdate": "no action"
        }
      },
      "compositePrimaryKeys": {},
      "uniqueConstraints": {}
    },
    "public.participants": {
      "name": "participants",
      "schema": "",
      "columns": {
        "id": {
          "name": "id",
          "type": "uuid",
          "primaryKey": true,
          "notNull": true,
          "default": "gen_random_uuid()"
        },
        "tenant_id": {
          "name": "tenant_id",
          "type": "uuid",
          "primaryKey": false,
          "notNull": true
        },
        "user_id": {
          "name": "user_id",
          "type": "uuid",
          "primaryKey": false,
          "notNull": false
        },
        "employee_id": {
          "name": "employee_id",
          "type": "text",
          "primaryKey": false,
          "notNull": false
        },
        "first_name": {
          "name": "first_name",
          "type": "text",
          "primaryKey": false,
          "notNull": true
        },
        "last_name": {
          "name": "last_name",
          "type": "text",
          "primaryKey": false,
          "notNull": true
        },
        "email": {
          "name": "email",
          "type": "text",
          "primaryKey": false,
          "notNull": true
        },
        "title": {
          "name": "title",
          "type": "text",
          "primaryKey": false,
          "notNull": false
        },
        "status": {
          "name": "status",
          "type": "text",
          "primaryKey": false,
          "notNull": true,
          "default": "'active'"
        },
        "hire_date": {
          "name": "hire_date",
          "type": "text",
          "primaryKey": false,
          "notNull": false
        },
        "termination_date": {
          "name": "termination_date",
          "type": "text",
          "primaryKey": false,
          "notNull": false
        },
        "metadata": {
          "name": "metadata",
          "type": "jsonb",
          "primaryKey": false,
          "notNull": true,
          "default": "'{}'::jsonb"
        },
        "created_at": {
          "name": "created_at",
          "type": "timestamp with time zone",
          "primaryKey": false,
          "notNull": true,
          "default": "now()"
        },
        "updated_at": {
          "name": "updated_at",
          "type": "timestamp with time zone",
          "primaryKey": false,
          "notNull": true,
          "default": "now()"
        },
        "deleted_at": {
          "name": "deleted_at",
          "type": "timestamp with time zone",
          "primaryKey": false,
          "notNull": false
        }
      },
      "indexes": {},
      "foreignKeys": {
        "participants_user_id_users_id_fk": {
          "name": "participants_user_id_users_id_fk",
          "tableFrom": "participants",
          "tableTo": "users",
          "columnsFrom": [
            "user_id"
          ],
          "columnsTo": [
            "id"
          ],
          "onDelete": "no action",
          "onUpdate": "no action"
        }
      },
      "compositePrimaryKeys": {},
      "uniqueConstraints": {}
    },
    "public.payouts": {
      "name": "payouts",
      "schema": "",
      "columns": {
        "id": {
          "name": "id",
          "type": "uuid",
          "primaryKey": true,
          "notNull": true,
          "default": "gen_random_uuid()"
        },
        "tenant_id": {
          "name": "tenant_id",
          "type": "uuid",
          "primaryKey": false,
          "notNull": true
        },
        "calculation_run_id": {
          "name": "calculation_run_id",
          "type": "uuid",
          "primaryKey": false,
          "notNull": true
        },
        "participant_id": {
          "name": "participant_id",
          "type": "uuid",
          "primaryKey": false,
          "notNull": true
        },
        "period_id": {
          "name": "period_id",
          "type": "uuid",
          "primaryKey": false,
          "notNull": true
        },
        "plan_version_id": {
          "name": "plan_version_id",
          "type": "uuid",
          "primaryKey": false,
          "notNull": true
        },
        "gross_amount_cents": {
          "name": "gross_amount_cents",
          "type": "integer",
          "primaryKey": false,
          "notNull": true
        },
        "adjusted_amount_cents": {
          "name": "adjusted_amount_cents",
          "type": "integer",
          "primaryKey": false,
          "notNull": true
        },
        "currency": {
          "name": "currency",
          "type": "text",
          "primaryKey": false,
          "notNull": true,
          "default": "'USD'"
        },
        "status": {
          "name": "status",
          "type": "text",
          "primaryKey": false,
          "notNull": true,
          "default": "'pending'"
        },
        "line_items": {
          "name": "line_items",
          "type": "jsonb",
          "primaryKey": false,
          "notNull": true,
          "default": "'[]'::jsonb"
        },
        "paid_at": {
          "name": "paid_at",
          "type": "timestamp with time zone",
          "primaryKey": false,
          "notNull": false
        },
        "created_at": {
          "name": "created_at",
          "type": "timestamp with time zone",
          "primaryKey": false,
          "notNull": true,
          "default": "now()"
        },
        "updated_at": {
          "name": "updated_at",
          "type": "timestamp with time zone",
          "primaryKey": false,
          "notNull": true,
          "default": "now()"
        }
      },
      "indexes": {},
      "foreignKeys": {
        "payouts_calculation_run_id_calculation_runs_id_fk": {
          "name": "payouts_calculation_run_id_calculation_runs_id_fk",
          "tableFrom": "payouts",
          "tableTo": "calculation_runs",
          "columnsFrom": [
            "calculation_run_id"
          ],
          "columnsTo": [
            "id"
          ],
          "onDelete": "no action",
          "onUpdate": "no action"
        },
        "payouts_participant_id_participants_id_fk": {
          "name": "payouts_participant_id_participants_id_fk",
          "tableFrom": "payouts",
          "tableTo": "participants",
          "columnsFrom": [
            "participant_id"
          ],
          "columnsTo": [
            "id"
          ],
          "onDelete": "no action",
          "onUpdate": "no action"
        },
        "payouts_period_id_periods_id_fk": {
          "name": "payouts_period_id_periods_id_fk",
          "tableFrom": "payouts",
          "tableTo": "periods",
          "columnsFrom": [
            "period_id"
          ],
          "columnsTo": [
            "id"
          ],
          "onDelete": "no action",
          "onUpdate": "no action"
        },
        "payouts_plan_version_id_plan_versions_id_fk": {
          "name": "payouts_plan_version_id_plan_versions_id_fk",
          "tableFrom": "payouts",
          "tableTo": "plan_versions",
          "columnsFrom": [
            "plan_version_id"
          ],
          "columnsTo": [
            "id"
          ],
          "onDelete": "no action",
          "onUpdate": "no action"
        }
      },
      "compositePrimaryKeys": {},
      "uniqueConstraints": {}
    },
    "public.periods": {
      "name": "periods",
      "schema": "",
      "columns": {
        "id": {
          "name": "id",
          "type": "uuid",
          "primaryKey": true,
          "notNull": true,
          "default": "gen_random_uuid()"
        },
        "tenant_id": {
          "name": "tenant_id",
          "type": "uuid",
          "primaryKey": false,
          "notNull": true
        },
        "name": {
          "name": "name",
          "type": "text",
          "primaryKey": false,
          "notNull": true
        },
        "start_date": {
          "name": "start_date",
          "type": "text",
          "primaryKey": false,
          "notNull": true
        },
        "end_date": {
          "name": "end_date",
          "type": "text",
          "primaryKey": false,
          "notNull": true
        },
        "is_closed": {
          "name": "is_closed",
          "type": "boolean",
          "primaryKey": false,
          "notNull": true,
          "default": false
        },
        "created_at": {
          "name": "created_at",
          "type": "timestamp with time zone",
          "primaryKey": false,
          "notNull": true,
          "default": "now()"
        },
        "updated_at": {
          "name": "updated_at",
          "type": "timestamp with time zone",
          "primaryKey": false,
          "notNull": true,
          "default": "now()"
        }
      },
      "indexes": {},
      "foreignKeys": {},
      "compositePrimaryKeys": {},
      "uniqueConstraints": {}
    },
    "public.plan_versions": {
      "name": "plan_versions",
      "schema": "",
      "columns": {
        "id": {
          "name": "id",
          "type": "uuid",
          "primaryKey": true,
          "notNull": true,
          "default": "gen_random_uuid()"
        },
        "tenant_id": {
          "name": "tenant_id",
          "type": "uuid",
          "primaryKey": false,
          "notNull": true
        },
        "plan_id": {
          "name": "plan_id",
          "type": "uuid",
          "primaryKey": false,
          "notNull": true
        },
        "version": {
          "name": "version",
          "type": "integer",
          "primaryKey": false,
          "notNull": true,
          "default": 1
        },
        "status": {
          "name": "status",
          "type": "text",
          "primaryKey": false,
          "notNull": true,
          "default": "'draft'"
        },
        "definition": {
          "name": "definition",
          "type": "jsonb",
          "primaryKey": false,
          "notNull": true
        },
        "published_at": {
          "name": "published_at",
          "type": "timestamp with time zone",
          "primaryKey": false,
          "notNull": false
        },
        "published_by_id": {
          "name": "published_by_id",
          "type": "uuid",
          "primaryKey": false,
          "notNull": false
        },
        "created_at": {
          "name": "created_at",
          "type": "timestamp with time zone",
          "primaryKey": false,
          "notNull": true,
          "default": "now()"
        },
        "updated_at": {
          "name": "updated_at",
          "type": "timestamp with time zone",
          "primaryKey": false,
          "notNull": true,
          "default": "now()"
        }
      },
      "indexes": {},
      "foreignKeys": {
        "plan_versions_plan_id_plans_id_fk": {
          "name": "plan_versions_plan_id_plans_id_fk",
          "tableFrom": "plan_versions",
          "tableTo": "plans",
          "columnsFrom": [
            "plan_id"
          ],
          "columnsTo": [
            "id"
          ],
          "onDelete": "no action",
          "onUpdate": "no action"
        },
        "plan_versions_published_by_id_users_id_fk": {
          "name": "plan_versions_published_by_id_users_id_fk",
          "tableFrom": "plan_versions",
          "tableTo": "users",
          "columnsFrom": [
            "published_by_id"
          ],
          "columnsTo": [
            "id"
          ],
          "onDelete": "no action",
          "onUpdate": "no action"
        }
      },
      "compositePrimaryKeys": {},
      "uniqueConstraints": {}
    },
    "public.plans": {
      "name": "plans",
      "schema": "",
      "columns": {
        "id": {
          "name": "id",
          "type": "uuid",
          "primaryKey": true,
          "notNull": true,
          "default": "gen_random_uuid()"
        },
        "tenant_id": {
          "name": "tenant_id",
          "type": "uuid",
          "primaryKey": false,
          "notNull": true
        },
        "name": {
          "name": "name",
          "type": "text",
          "primaryKey": false,
          "notNull": true
        },
        "description": {
          "name": "description",
          "type": "text",
          "primaryKey": false,
          "notNull": false
        },
        "status": {
          "name": "status",
          "type": "text",
          "primaryKey": false,
          "notNull": true,
          "default": "'draft'"
        },
        "effective_from": {
          "name": "effective_from",
          "type": "text",
          "primaryKey": false,
          "notNull": true
        },
        "effective_to": {
          "name": "effective_to",
          "type": "text",
          "primaryKey": false,
          "notNull": false
        },
        "currency": {
          "name": "currency",
          "type": "text",
          "primaryKey": false,
          "notNull": true,
          "default": "'USD'"
        },
        "metadata": {
          "name": "metadata",
          "type": "jsonb",
          "primaryKey": false,
          "notNull": true,
          "default": "'{}'::jsonb"
        },
        "created_at": {
          "name": "created_at",
          "type": "timestamp with time zone",
          "primaryKey": false,
          "notNull": true,
          "default": "now()"
        },
        "updated_at": {
          "name": "updated_at",
          "type": "timestamp with time zone",
          "primaryKey": false,
          "notNull": true,
          "default": "now()"
        },
        "deleted_at": {
          "name": "deleted_at",
          "type": "timestamp with time zone",
          "primaryKey": false,
          "notNull": false
        }
      },
      "indexes": {},
      "foreignKeys": {},
      "compositePrimaryKeys": {},
      "uniqueConstraints": {}
    },
    "public.quotas": {
      "name": "quotas",
      "schema": "",
      "columns": {
        "id": {
          "name": "id",
          "type": "uuid",
          "primaryKey": true,
          "notNull": true,
          "default": "gen_random_uuid()"
        },
        "tenant_id": {
          "name": "tenant_id",
          "type": "uuid",
          "primaryKey": false,
          "notNull": true
        },
        "participant_id": {
          "name": "participant_id",
          "type": "uuid",
          "primaryKey": false,
          "notNull": true
        },
        "plan_version_id": {
          "name": "plan_version_id",
          "type": "uuid",
          "primaryKey": false,
          "notNull": true
        },
        "period_id": {
          "name": "period_id",
          "type": "uuid",
          "primaryKey": false,
          "notNull": true
        },
        "type": {
          "name": "type",
          "type": "text",
          "primaryKey": false,
          "notNull": true,
          "default": "'revenue'"
        },
        "amount": {
          "name": "amount",
          "type": "integer",
          "primaryKey": false,
          "notNull": true
        },
        "currency": {
          "name": "currency",
          "type": "text",
          "primaryKey": false,
          "notNull": true,
          "default": "'USD'"
        },
        "notes": {
          "name": "notes",
          "type": "text",
          "primaryKey": false,
          "notNull": false
        },
        "created_at": {
          "name": "created_at",
          "type": "timestamp with time zone",
          "primaryKey": false,
          "notNull": true,
          "default": "now()"
        },
        "updated_at": {
          "name": "updated_at",
          "type": "timestamp with time zone",
          "primaryKey": false,
          "notNull": true,
          "default": "now()"
        }
      },
      "indexes": {},
      "foreignKeys": {
        "quotas_participant_id_participants_id_fk": {
          "name": "quotas_participant_id_participants_id_fk",
          "tableFrom": "quotas",
          "tableTo": "participants",
          "columnsFrom": [
            "participant_id"
          ],
          "columnsTo": [
            "id"
          ],
          "onDelete": "no action",
          "onUpdate": "no action"
        },
        "quotas_plan_version_id_plan_versions_id_fk": {
          "name": "quotas_plan_version_id_plan_versions_id_fk",
          "tableFrom": "quotas",
          "tableTo": "plan_versions",
          "columnsFrom": [
            "plan_version_id"
          ],
          "columnsTo": [
            "id"
          ],
          "onDelete": "no action",
          "onUpdate": "no action"
        },
        "quotas_period_id_periods_id_fk": {
          "name": "quotas_period_id_periods_id_fk",
          "tableFrom": "quotas",
          "tableTo": "periods",
          "columnsFrom": [
            "period_id"
          ],
          "columnsTo": [
            "id"
          ],
          "onDelete": "no action",
          "onUpdate": "no action"
        }
      },
      "compositePrimaryKeys": {},
      "uniqueConstraints": {}
    },
    "public.source_transactions": {
      "name": "source_transactions",
      "schema": "",
      "columns": {
        "id": {
          "name": "id",
          "type": "uuid",
          "primaryKey": true,
          "notNull": true,
          "default": "gen_random_uuid()"
        },
        "tenant_id": {
          "name": "tenant_id",
          "type": "uuid",
          "primaryKey": false,
          "notNull": true
        },
        "external_id": {
          "name": "external_id",
          "type": "text",
          "primaryKey": false,
          "notNull": true
        },
        "source": {
          "name": "source",
          "type": "text",
          "primaryKey": false,
          "notNull": true
        },
        "participant_id": {
          "name": "participant_id",
          "type": "uuid",
          "primaryKey": false,
          "notNull": false
        },
        "transaction_date": {
          "name": "transaction_date",
          "type": "text",
          "primaryKey": false,
          "notNull": true
        },
        "amount_cents": {
          "name": "amount_cents",
          "type": "integer",
          "primaryKey": false,
          "notNull": true
        },
        "currency": {
          "name": "currency",
          "type": "text",
          "primaryKey": false,
          "notNull": true,
          "default": "'USD'"
        },
        "status": {
          "name": "status",
          "type": "text",
          "primaryKey": false,
          "notNull": true,
          "default": "'pending'"
        },
        "payload": {
          "name": "payload",
          "type": "jsonb",
          "primaryKey": false,
          "notNull": true
        },
        "validation_errors": {
          "name": "validation_errors",
          "type": "jsonb",
          "primaryKey": false,
          "notNull": true,
          "default": "'[]'::jsonb"
        },
        "processed_at": {
          "name": "processed_at",
          "type": "timestamp with time zone",
          "primaryKey": false,
          "notNull": false
        },
        "created_at": {
          "name": "created_at",
          "type": "timestamp with time zone",
          "primaryKey": false,
          "notNull": true,
          "default": "now()"
        },
        "updated_at": {
          "name": "updated_at",
          "type": "timestamp with time zone",
          "primaryKey": false,
          "notNull": true,
          "default": "now()"
        }
      },
      "indexes": {},
      "foreignKeys": {
        "source_transactions_participant_id_participants_id_fk": {
          "name": "source_transactions_participant_id_participants_id_fk",
          "tableFrom": "source_transactions",
          "tableTo": "participants",
          "columnsFrom": [
            "participant_id"
          ],
          "columnsTo": [
            "id"
          ],
          "onDelete": "no action",
          "onUpdate": "no action"
        }
      },
      "compositePrimaryKeys": {},
      "uniqueConstraints": {}
    },
    "public.tenants": {
      "name": "tenants",
      "schema": "",
      "columns": {
        "id": {
          "name": "id",
          "type": "uuid",
          "primaryKey": true,
          "notNull": true,
          "default": "gen_random_uuid()"
        },
        "name": {
          "name": "name",
          "type": "text",
          "primaryKey": false,
          "notNull": true
        },
        "slug": {
          "name": "slug",
          "type": "text",
          "primaryKey": false,
          "notNull": true
        },
        "settings": {
          "name": "settings",
          "type": "jsonb",
          "primaryKey": false,
          "notNull": true,
          "default": "'{}'::jsonb"
        },
        "created_at": {
          "name": "created_at",
          "type": "timestamp with time zone",
          "primaryKey": false,
          "notNull": true,
          "default": "now()"
        },
        "updated_at": {
          "name": "updated_at",
          "type": "timestamp with time zone",
          "primaryKey": false,
          "notNull": true,
          "default": "now()"
        }
      },
      "indexes": {},
      "foreignKeys": {},
      "compositePrimaryKeys": {},
      "uniqueConstraints": {
        "tenants_slug_unique": {
          "name": "tenants_slug_unique",
          "nullsNotDistinct": false,
          "columns": [
            "slug"
          ]
        }
      }
    },
    "public.users": {
      "name": "users",
      "schema": "",
      "columns": {
        "id": {
          "name": "id",
          "type": "uuid",
          "primaryKey": true,
          "notNull": true,
          "default": "gen_random_uuid()"
        },
        "tenant_id": {
          "name": "tenant_id",
          "type": "uuid",
          "primaryKey": false,
          "notNull": true
        },
        "email": {
          "name": "email",
          "type": "text",
          "primaryKey": false,
          "notNull": true
        },
        "first_name": {
          "name": "first_name",
          "type": "text",
          "primaryKey": false,
          "notNull": true
        },
        "last_name": {
          "name": "last_name",
          "type": "text",
          "primaryKey": false,
          "notNull": true
        },
        "password_hash": {
          "name": "password_hash",
          "type": "text",
          "primaryKey": false,
          "notNull": true
        },
        "role": {
          "name": "role",
          "type": "text",
          "primaryKey": false,
          "notNull": true
        },
        "is_active": {
          "name": "is_active",
          "type": "boolean",
          "primaryKey": false,
          "notNull": true,
          "default": true
        },
        "last_login_at": {
          "name": "last_login_at",
          "type": "timestamp with time zone",
          "primaryKey": false,
          "notNull": false
        },
        "created_at": {
          "name": "created_at",
          "type": "timestamp with time zone",
          "primaryKey": false,
          "notNull": true,
          "default": "now()"
        },
        "updated_at": {
          "name": "updated_at",
          "type": "timestamp with time zone",
          "primaryKey": false,
          "notNull": true,
          "default": "now()"
        },
        "deleted_at": {
          "name": "deleted_at",
          "type": "timestamp with time zone",
          "primaryKey": false,
          "notNull": false
        }
      },
      "indexes": {},
      "foreignKeys": {},
      "compositePrimaryKeys": {},
      "uniqueConstraints": {}
    }
  },
  "enums": {},
  "schemas": {},
  "_meta": {
    "columns": {},
    "schemas": {},
    "tables": {}
  }
}